{"_astro/bagel-paper.e6d51f9b_Z24SXrC.avif":{"expires":1715205347896},"_astro/stoneway-alt.7414a06e_KGrVt.avif":{"expires":1715205347901},"_astro/bagel-halves.0314bb19_Z1XdlqI.avif":{"expires":1715205347893},"_astro/menu-hero.529ad811_GQNcG.avif":{"expires":1715205347897},"_astro/hero.3199ec64_ZbWUM3.avif":{"expires":1715205347894},"_astro/poppy.04e0f4f3_KYI5T.avif":{"expires":1715205347895},"_astro/menu-3.e602c7de_ZTvXN7.avif":{"expires":1715205347902},"_astro/menu-2.0aa14460_1B3FaD.avif":{"expires":1715205347904},"_astro/menu-1.2f13b7d0_1XmmOi.avif":{"expires":1715205347903},"_astro/coffee-beans.37fc4a11_1sVzCG.avif":{"expires":1715205347895},"_astro/neighborhood-delivery-menu.b3b000d8_2ksKVx.avif":{"expires":1715205347904},"_astro/stoneway.7e27c467_ZEL4j5.avif":{"expires":1715205347903},"_astro/spread-grid.e91aaafb_Z1eNI3f.avif":{"expires":1715205347899},"_astro/rainbow-spread.35f6e4c7_ZID6hb.avif":{"expires":1715205347905},"_astro/capitol-hill.80aa5d36_ZmQl5R.avif":{"expires":1715205347904},"_astro/default.814ae9ef_Z1TQ0AR.png":{"expires":1715205347885},"_astro/bagel-paper.e6d51f9b_2nUaYc.avif":{"expires":1715205347896},"_astro/stoneway-alt.7414a06e_ZHeS8.avif":{"expires":1715205347901},"_astro/hero.3199ec64_cUFxJ.avif":{"expires":1715205347894},"_astro/bagel-halves.0314bb19_2kz5xB.avif":{"expires":1715205347893},"_astro/coffee-beans.37fc4a11_GwRN5.avif":{"expires":1715205347895},"_astro/stoneway.7e27c467_ZfRrXi.avif":{"expires":1715205347903},"_astro/menu-hero.529ad811_5tNOz.avif":{"expires":1715205347897},"_astro/spread-grid.e91aaafb_ZOU6Hs.avif":{"expires":1715205347899},"_astro/menu-2.0aa14460_ZdVdSU.avif":{"expires":1715205347904},"_astro/poppy.04e0f4f3_9BIHM.avif":{"expires":1715205347895},"_astro/menu-1.2f13b7d0_Va9Bx.avif":{"expires":1715205347903},"_astro/bagel-paper.e6d51f9b_Z1VBdMa.webp":{"expires":1715205347896},"_astro/stoneway-alt.7414a06e_SYcAV.webp":{"expires":1715205347901},"_astro/capitol-hill.80aa5d36_Z19g2Ut.avif":{"expires":1715205347904},"_astro/bagel-halves.0314bb19_Z1OUALg.webp":{"expires":1715205347893},"_astro/rainbow-spread.35f6e4c7_Z1v2N6M.avif":{"expires":1715205347905},"_astro/coffee-beans.37fc4a11_1Beki9.webp":{"expires":1715205347895},"_astro/menu-3.e602c7de_Z204mYh.avif":{"expires":1715205347902},"_astro/menu-hero.529ad811_P9xR9.webp":{"expires":1715205347897},"_astro/neighborhood-delivery-menu.b3b000d8_2017Ei.avif":{"expires":1715205347904},"_astro/poppy.04e0f4f3_ThsKm.webp":{"expires":1715205347895},"_astro/stoneway-alt.7414a06e_7zuLk.webp":{"expires":1715205347901},"_astro/hero.3199ec64_1IUMsJ.avif":{"expires":1715205347894},"_astro/bagel-paper.e6d51f9b_2wcUDE.webp":{"expires":1715205347896},"_astro/bagel-halves.0314bb19_2sQPd4.webp":{"expires":1715205347893},"_astro/coffee-beans.37fc4a11_OOCsx.webp":{"expires":1715205347895},"_astro/menu-hero.529ad811_dLyu2.webp":{"expires":1715205347897},"_astro/poppy.04e0f4f3_hTtnf.webp":{"expires":1715205347895},"_astro/capitol-hill.80aa5d36_ZeyAqp.webp":{"expires":1715205347904},"_astro/stoneway.7e27c467_2lxSDw.avif":{"expires":1715205347903},"_astro/rainbow-spread.35f6e4c7_Z1J3Ysg.avif":{"expires":1715205347905},"_astro/stoneway-alt.7414a06e_2FkbY.jpg":{"expires":1715205347901},"_astro/bagel-paper.e6d51f9b_259OA5.jpg":{"expires":1715205347896},"_astro/bagel-halves.0314bb19_2fnmzK.jpg":{"expires":1715205347893},"_astro/spread-grid.e91aaafb_ZcbQPK.avif":{"expires":1715205347899},"_astro/coffee-beans.37fc4a11_2m9TTz.jpg":{"expires":1715205347895},"_astro/menu-hero.529ad811_Z7rAss.jpg":{"expires":1715205347897},"_astro/menu-2.0aa14460_2hJY7n.avif":{"expires":1715205347904},"_astro/poppy.04e0f4f3_GHtIj.jpg":{"expires":1715205347895},"_astro/capitol-hill.80aa5d36_Z10Xig1.webp":{"expires":1715205347904},"_astro/stoneway-alt.7414a06e_29e8J4.jpg":{"expires":1715205347901},"_astro/menu-1.2f13b7d0_Z2fAdqR.avif":{"expires":1715205347903},"_astro/neighborhood-delivery-menu.b3b000d8_bBU2T.avif":{"expires":1715205347904},"_astro/bagel-halves.0314bb19_ZIfWG6.jpg":{"expires":1715205347893},"_astro/bagel-paper.e6d51f9b_Z1Rc7n0.jpg":{"expires":1715205347896},"_astro/coffee-beans.37fc4a11_ZBtpmh.jpg":{"expires":1715205347895},"_astro/menu-hero.529ad811_10nAno.jpg":{"expires":1715205347897},"_astro/hero.3199ec64_1MYJBy.avif":{"expires":1715205347894},"_astro/poppy.04e0f4f3_1OxFza.jpg":{"expires":1715205347895},"_astro/menu-3.e602c7de_Z1Nobps.avif":{"expires":1715205347902},"_astro/capitol-hill.80aa5d36_ZNAu23.jpg":{"expires":1715205347904},"_astro/bagel-paper.e6d51f9b_Z2ePher.avif":{"expires":1715205347896},"_astro/hero.3199ec64_Z3Fb7A.webp":{"expires":1715205347894},"_astro/stoneway.7e27c467_zyiOd.avif":{"expires":1715205347903},"_astro/menu-hero.529ad811_16Kpxt.avif":{"expires":1715205347897},"_astro/capitol-hill.80aa5d36_1hWjv2.jpg":{"expires":1715205347904},"_astro/rainbow-spread.35f6e4c7_1T1zvG.avif":{"expires":1715205347905},"_astro/hero.3199ec64_ldqdc.webp":{"expires":1715205347894},"_astro/stoneway.7e27c467_ZwtjDC.webp":{"expires":1715205347903},"_astro/spread-grid.e91aaafb_Z2hH9hp.avif":{"expires":1715205347899},"_astro/menu-hero.529ad811_ZTtcz0.avif":{"expires":1715205347897},"_astro/rainbow-spread.35f6e4c7_ZAllBI.webp":{"expires":1715205347905},"_astro/hero.3199ec64_1Rdx8c.webp":{"expires":1715205347894},"_astro/stoneway.7e27c467_Z7zHiP.webp":{"expires":1715205347903},"_astro/spread-grid.e91aaafb_Z16vXnM.webp":{"expires":1715205347899},"_astro/bagel-paper.e6d51f9b_Z5t4d3.avif":{"expires":1715205347896},"_astro/menu-2.0aa14460_1vyrIs.avif":{"expires":1715205347904},"_astro/rainbow-spread.35f6e4c7_Z1mK3rk.webp":{"expires":1715205347905},"_astro/hero.3199ec64_1Vhuh1.webp":{"expires":1715205347894},"_astro/stoneway.7e27c467_2tPDiY.webp":{"expires":1715205347903},"_astro/bagel-paper.e6d51f9b_Z26xwyY.webp":{"expires":1715205347896},"_astro/menu-2.0aa14460_1JlpP6.webp":{"expires":1715205347904},"_astro/spread-grid.e91aaafb_ZGCm30.webp":{"expires":1715205347899},"_astro/rainbow-spread.35f6e4c7_Z1ALeMN.webp":{"expires":1715205347905},"_astro/hero.3199ec64_2sRLiX.jpg":{"expires":1715205347894},"_astro/bagel-paper.e6d51f9b_2NFrp.webp":{"expires":1715205347896},"_astro/menu-2.0aa14460_Z5Dtes.webp":{"expires":1715205347904},"_astro/spread-grid.e91aaafb_Z3T7bi.webp":{"expires":1715205347899},"_astro/menu-1.2f13b7d0_23pnY9.avif":{"expires":1715205347903},"_astro/neighborhood-delivery-menu.b3b000d8_ZzyBl1.avif":{"expires":1715205347904},"_astro/hero.3199ec64_2jFmDF.jpg":{"expires":1715205347894},"_astro/bagel-paper.e6d51f9b_2ePEqj.jpg":{"expires":1715205347896},"_astro/stoneway.7e27c467_HQ3tF.webp":{"expires":1715205347903},"_astro/menu-1.2f13b7d0_26E7tK.webp":{"expires":1715205347903},"_astro/menu-2.0aa14460_2q2ILP.webp":{"expires":1715205347904},"_astro/neighborhood-delivery-menu.b3b000d8_2sKvB0.webp":{"expires":1715205347904},"_astro/bagel-paper.e6d51f9b_b03GN.jpg":{"expires":1715205347896},"_astro/hero.3199ec64_1REcb4.jpg":{"expires":1715205347894},"_astro/menu-1.2f13b7d0_14rTh0.webp":{"expires":1715205347903},"_astro/stoneway.7e27c467_1WUU1i.jpg":{"expires":1715205347903},"_astro/neighborhood-delivery-menu.b3b000d8_28iRjK.webp":{"expires":1715205347904},"_astro/rainbow-spread.35f6e4c7_22jkb9.webp":{"expires":1715205347905},"_astro/spread-grid.e91aaafb_Z29poBW.webp":{"expires":1715205347899},"_astro/bagel-paper.e6d51f9b_Z1F0m6P.avif":{"expires":1715205347896},"_astro/menu-1.2f13b7d0_Z27isLp.webp":{"expires":1715205347903},"_astro/stoneway.7e27c467_1NIvm0.jpg":{"expires":1715205347903},"_astro/hero.3199ec64_1xLphX.jpg":{"expires":1715205347894},"_astro/rainbow-spread.35f6e4c7_Z1mmEvc.png":{"expires":1715205347905},"_astro/neighborhood-delivery-menu.b3b000d8_jTEHm.webp":{"expires":1715205347904},"_astro/spread-grid.e91aaafb_ZlhvSc.jpg":{"expires":1715205347899},"_astro/menu-2.0aa14460_1DQcnU.webp":{"expires":1715205347904},"_astro/menu-hero.529ad811_18t2jD.avif":{"expires":1715205347897},"_astro/bagel-paper.e6d51f9b_ZIQX8L.avif":{"expires":1715205347896},"_astro/menu-2.0aa14460_13mJVw.jpg":{"expires":1715205347904},"_astro/stoneway.7e27c467_1oQ3E2.jpg":{"expires":1715205347903},"_astro/menu-hero.529ad811_1f3acV.webp":{"expires":1715205347897},"_astro/rainbow-spread.35f6e4c7_Jb91S.png":{"expires":1715205347905},"_astro/spread-grid.e91aaafb_ZutUxu.jpg":{"expires":1715205347899},"_astro/menu-3.e602c7de_2uBq0y.avif":{"expires":1715205347902},"_astro/menu-2.0aa14460_1tLxd1.jpg":{"expires":1715205347904},"_astro/menu-hero.529ad811_ZLbrTx.webp":{"expires":1715205347897},"_astro/menu-3.e602c7de_ZLee8E.webp":{"expires":1715205347902},"_astro/spread-grid.e91aaafb_ONoTR.jpg":{"expires":1715205347899},"_astro/menu-2.0aa14460_ZokIxO.jpg":{"expires":1715205347904},"_astro/menu-1.2f13b7d0_2bH8DB.webp":{"expires":1715205347903},"_astro/stoneway.7e27c467_2aovsK.jpg":{"expires":1715205347903},"_astro/neighborhood-delivery-menu.b3b000d8_ZrgQFy.webp":{"expires":1715205347904},"_astro/menu-3.e602c7de_Z1QLCjO.webp":{"expires":1715205347902},"_astro/menu-1.2f13b7d0_p44Qm.jpg":{"expires":1715205347903},"_astro/menu-hero.529ad811_1gKLY6.webp":{"expires":1715205347897},"_astro/neighborhood-delivery-menu.b3b000d8_Z1xi7Bz.jpg":{"expires":1715205347904},"_astro/rainbow-spread.35f6e4c7_22LGpS.png":{"expires":1715205347905},"_astro/menu-hero.529ad811_ZgE07K.jpg":{"expires":1715205347897},"_astro/menu-1.2f13b7d0_1Q5eQF.jpg":{"expires":1715205347903},"_astro/menu-3.e602c7de_Z1F6qK0.webp":{"expires":1715205347902},"_astro/neighborhood-delivery-menu.b3b000d8_2dbCXU.jpg":{"expires":1715205347904},"_astro/menu-hero.529ad811_Z2iHcD8.jpg":{"expires":1715205347897},"_astro/menu-1.2f13b7d0_KKDWD.jpg":{"expires":1715205347903},"_astro/neighborhood-delivery-menu.b3b000d8_1OBC0o.jpg":{"expires":1715205347904},"_astro/spread-grid.e91aaafb_Znlf1w.jpg":{"expires":1715205347899},"_astro/menu-2.0aa14460_Z5PMWU.jpg":{"expires":1715205347904},"_astro/menu-hero.529ad811_Z15CzJL.jpg":{"expires":1715205347897},"_astro/menu-3.e602c7de_Z2rhX8U.webp":{"expires":1715205347902},"_astro/menu-3.e602c7de_1Mrukm.jpg":{"expires":1715205347902},"_astro/menu-1.2f13b7d0_14fzxx.jpg":{"expires":1715205347903},"_astro/neighborhood-delivery-menu.b3b000d8_286xAi.jpg":{"expires":1715205347904},"_astro/menu-3.e602c7de_Z11N6KJ.jpg":{"expires":1715205347902},"_astro/menu-3.e602c7de_Z2asRDb.jpg":{"expires":1715205347902},"_astro/menu-3.e602c7de_Z1QXW3h.jpg":{"expires":1715205347902},"_astro/rainbow-spread.35f6e4c7_Zs9xN7.png":{"expires":1715205347905},"_astro/rainbow-spread.35f6e4c7_cPwmn.avif":{"expires":1715205347905},"_astro/rainbow-spread.35f6e4c7_Zyyase.avif":{"expires":1715205347905},"_astro/rainbow-spread.35f6e4c7_l8h1P.webp":{"expires":1715205347905},"_astro/rainbow-spread.35f6e4c7_ZqgpML.webp":{"expires":1715205347905},"_astro/rainbow-spread.35f6e4c7_Z1spb8.png":{"expires":1715205347905},"_astro/rainbow-spread.35f6e4c7_255olW.png":{"expires":1715205347905},"_astro/bagel-paper.e6d51f9b_1rcdOO.avif":{"expires":1715205347896},"_astro/bagel-paper.e6d51f9b_Z1wHBrn.webp":{"expires":1715205347896},"_astro/bagel-paper.e6d51f9b_ZAzdtj.webp":{"expires":1715205347896},"_astro/bagel-paper.e6d51f9b_1ztXuh.webp":{"expires":1715205347896},"_astro/bagel-paper.e6d51f9b_1UWpUM.jpg":{"expires":1715205347896},"_astro/bagel-paper.e6d51f9b_ZgPtv.jpg":{"expires":1715205347896},"_astro/bagel-paper.e6d51f9b_ZU1ljx.jpg":{"expires":1715205347896},"_astro/side-kick-1.0b795058_R6FsI.avif":{"expires":1715242098963},"_astro/side-kick-1.0b795058_1h0hNv.avif":{"expires":1715242098963},"_astro/side-kick-1.0b795058_ZM7heU.avif":{"expires":1715242098963},"_astro/side-kick-1.0b795058_ZczthK.avif":{"expires":1715242098963},"_astro/side-kick-1.0b795058_10oq8b.webp":{"expires":1715242098963},"_astro/side-kick-1.0b795058_1pi2sX.webp":{"expires":1715242098963},"_astro/side-kick-1.0b795058_ZDOwzs.webp":{"expires":1715242098963},"_astro/side-kick-1.0b795058_Z4hICi.webp":{"expires":1715242098963},"_astro/side-kick-1.0b795058_Zh7OLg.jpg":{"expires":1715242098963},"_astro/side-kick-1.0b795058_Zqkeqy.jpg":{"expires":1715242098963},"_astro/side-kick-1.0b795058_Z28skn6.jpg":{"expires":1715242098963},"_astro/side-kick-1.0b795058_ZXgEpG.jpg":{"expires":1715242098963},"_astro/bagel-paper.e6d51f9b_D043o.avif":{"expires":1715525935755},"_astro/hero.3199ec64_Z1jiWug.avif":{"expires":1715525935755},"_astro/bagel-halves.0314bb19_Z2iLR7T.avif":{"expires":1715525935754},"_astro/menu-hero.529ad811_Z23r5gA.avif":{"expires":1715525935755},"_astro/stoneway-alt.7414a06e_Z1o5zKe.avif":{"expires":1715525935756},"_astro/poppy.04e0f4f3_Z1wNc7r.avif":{"expires":1715525935755},"_astro/coffee-beans.37fc4a11_Z1XxJzw.avif":{"expires":1715525935756},"_astro/side-kick-1.0b795058_ZfFNOD.avif":{"expires":1715525935756},"_astro/stoneway.7e27c467_1VNXCL.avif":{"expires":1715525935757},"_astro/capitol-hill.80aa5d36_ZUKgPG.avif":{"expires":1715525935756},"_astro/menu-1.2f13b7d0_Z1dm8pB.avif":{"expires":1715525935757},"_astro/default.814ae9ef_ZsrvyL.png":{"expires":1715525935753},"_astro/menu-3.e602c7de_ipqrd.avif":{"expires":1715525935757},"_astro/menu-2.0aa14460_2p2OjP.avif":{"expires":1715525935757},"_astro/neighborhood-delivery-menu.b3b000d8_1OTq62.avif":{"expires":1715525935757},"_astro/rainbow-spread.35f6e4c7_pwiDb.avif":{"expires":1715525936577},"_astro/hero.3199ec64_2rwVr8.avif":{"expires":1715525935755},"_astro/bagel-paper.e6d51f9b_Z1LRlsV.avif":{"expires":1715525935755},"_astro/menu-hero.529ad811_ARD11.avif":{"expires":1715525935755},"_astro/bagel-halves.0314bb19_Z1TC7F0.avif":{"expires":1715525935754},"_astro/side-kick-1.0b795058_Z1z23Hb.avif":{"expires":1715525935756},"_astro/coffee-beans.37fc4a11_Z1zo07C.avif":{"expires":1715525935756},"_astro/poppy.04e0f4f3_17vwaa.avif":{"expires":1715525935755},"_astro/stoneway.7e27c467_CsIKe.avif":{"expires":1715525935757},"_astro/capitol-hill.80aa5d36_ZwAwnM.avif":{"expires":1715525935756},"_astro/menu-1.2f13b7d0_ZPv9uf.avif":{"expires":1715525935757},"_astro/menu-3.e602c7de_wRfXK.avif":{"expires":1715525935757},"_astro/stoneway-alt.7414a06e_ZYUPik.avif":{"expires":1715525935756},"_astro/menu-2.0aa14460_Zcctp5.avif":{"expires":1715525935757},"_astro/bagel-paper.e6d51f9b_1q6p59.webp":{"expires":1715525935755},"_astro/menu-hero.529ad811_Z1gkJeP.webp":{"expires":1715525935755},"_astro/bagel-halves.0314bb19_Z1vFw69.webp":{"expires":1715525935754},"_astro/neighborhood-delivery-menu.b3b000d8_2hjLPK.avif":{"expires":1715525935757},"_astro/coffee-beans.37fc4a11_Z1broxL.webp":{"expires":1715525935756},"_astro/poppy.04e0f4f3_ZJGQ5G.webp":{"expires":1715525935755},"_astro/hero.3199ec64_sA4uu.avif":{"expires":1715525935755},"_astro/capitol-hill.80aa5d36_Z8DUNV.webp":{"expires":1715525935756},"_astro/rainbow-spread.35f6e4c7_NG365.avif":{"expires":1715525936577},"_astro/side-kick-1.0b795058_Z2hpwzJ.avif":{"expires":1715525935756},"_astro/stoneway-alt.7414a06e_ZAYeIt.webp":{"expires":1715525935756},"_astro/stoneway.7e27c467_Z2lLMb.avif":{"expires":1715525935757},"_astro/bagel-paper.e6d51f9b_ZYL0rb.webp":{"expires":1715525935755},"_astro/menu-hero.529ad811_1nXY2L.webp":{"expires":1715525935755},"_astro/bagel-halves.0314bb19_Z17vLDf.webp":{"expires":1715525935754},"_astro/menu-1.2f13b7d0_1zrdhI.avif":{"expires":1715525935757},"_astro/coffee-beans.37fc4a11_ZMhE5R.webp":{"expires":1715525935756},"_astro/poppy.04e0f4f3_1TBRbU.webp":{"expires":1715525935755},"_astro/menu-3.e602c7de_Z1ir8kG.avif":{"expires":1715525935757},"_astro/capitol-hill.80aa5d36_fuNCX.webp":{"expires":1715525935756},"_astro/menu-2.0aa14460_1d8vD4.avif":{"expires":1715525935757},"_astro/neighborhood-delivery-menu.b3b000d8_1VxBoX.avif":{"expires":1715525935757},"_astro/stoneway-alt.7414a06e_ZcOugz.webp":{"expires":1715525935756},"_astro/hero.3199ec64_hVy9q.avif":{"expires":1715525935755},"_astro/bagel-paper.e6d51f9b_Z28Pssy.jpg":{"expires":1715525935755},"_astro/menu-hero.529ad811_ZU5U0z.jpg":{"expires":1715525935755},"_astro/bagel-halves.0314bb19_HsNzu.jpg":{"expires":1715525935754},"_astro/rainbow-spread.35f6e4c7_Z1gOp6d.avif":{"expires":1715525936577},"_astro/coffee-beans.37fc4a11_1Ramik.jpg":{"expires":1715525935756},"_astro/poppy.04e0f4f3_Z1y6e4K.jpg":{"expires":1715525935755},"_astro/side-kick-1.0b795058_1m1apc.avif":{"expires":1715525935756},"_astro/capitol-hill.80aa5d36_2of4oB.jpg":{"expires":1715525935756},"_astro/stoneway.7e27c467_ZaQzmB.avif":{"expires":1715525935757},"_astro/menu-1.2f13b7d0_Z2l6MLk.avif":{"expires":1715525935757},"_astro/stoneway-alt.7414a06e_Z2wQqnx.jpg":{"expires":1715525935756},"_astro/hero.3199ec64_ZwcBsv.webp":{"expires":1715525935755},"_astro/bagel-paper.e6d51f9b_SuYIi.jpg":{"expires":1715525935755},"_astro/menu-hero.529ad811_27fxbh.jpg":{"expires":1715525935755},"_astro/bagel-halves.0314bb19_2ciRB7.jpg":{"expires":1715525935754},"_astro/menu-2.0aa14460_2mLDnW.avif":{"expires":1715525935757},"_astro/coffee-beans.37fc4a11_Z1IbHtY.jpg":{"expires":1715525935756},"_astro/poppy.04e0f4f3_1tfe76.jpg":{"expires":1715525935755},"_astro/side-kick-1.0b795058_wpwc7.webp":{"expires":1715525935756},"_astro/capitol-hill.80aa5d36_Z1c70nH.jpg":{"expires":1715525935756},"_astro/menu-3.e602c7de_Z8N0zN.avif":{"expires":1715525935757},"_astro/stoneway.7e27c467_Z2lgO9p.webp":{"expires":1715525935757},"_astro/stoneway-alt.7414a06e_Z131mlU.jpg":{"expires":1715525935756},"_astro/menu-1.2f13b7d0_ZqfMnQ.webp":{"expires":1715525935757},"_astro/hero.3199ec64_Z1PxQl3.webp":{"expires":1715525935755},"_astro/bagel-paper.e6d51f9b_9hVXf.avif":{"expires":1715525935755},"_astro/menu-hero.529ad811_1HoNEN.avif":{"expires":1715525935755},"_astro/menu-2.0aa14460_Z1S2Xsl.webp":{"expires":1715525935757},"_astro/menu-3.e602c7de_15vLsX.webp":{"expires":1715525935757},"_astro/side-kick-1.0b795058_ZLUHFq.webp":{"expires":1715525935756},"_astro/stoneway.7e27c467_1pz4LY.webp":{"expires":1715525935757},"_astro/menu-1.2f13b7d0_Z3oNsu.webp":{"expires":1715525935757},"_astro/hero.3199ec64_1fGpwf.webp":{"expires":1715525935755},"_astro/neighborhood-delivery-menu.b3b000d8_Z1Y0oE5.avif":{"expires":1715525935757},"_astro/menu-2.0aa14460_zSQBF.webp":{"expires":1715525935757},"_astro/menu-3.e602c7de_1jXB0v.webp":{"expires":1715525935757},"_astro/side-kick-1.0b795058_Z1ujbxY.webp":{"expires":1715525935756},"_astro/menu-hero.529ad811_Z27JigV.avif":{"expires":1715525935755},"_astro/stoneway.7e27c467_JJyez.webp":{"expires":1715525935757},"_astro/menu-1.2f13b7d0_2mxyjt.webp":{"expires":1715525935757},"_astro/neighborhood-delivery-menu.b3b000d8_Z2sbmG9.webp":{"expires":1715525935757},"_astro/menu-2.0aa14460_20eQEO.webp":{"expires":1715525935757},"_astro/hero.3199ec64_152Tbb.webp":{"expires":1715525935755},"_astro/menu-3.e602c7de_ZvkMiV.webp":{"expires":1715525935757},"_astro/side-kick-1.0b795058_297vqW.webp":{"expires":1715525935756},"_astro/stoneway.7e27c467_BeKE9.webp":{"expires":1715525935757},"_astro/menu-1.2f13b7d0_Z1y0rJz.webp":{"expires":1715525935757},"_astro/neighborhood-delivery-menu.b3b000d8_Z20L0Vq.webp":{"expires":1715525935757},"_astro/menu-hero.529ad811_1bLi9a.avif":{"expires":1715525935755},"_astro/hero.3199ec64_2dtktA.jpg":{"expires":1715525935755},"_astro/menu-2.0aa14460_Z1Uj9oe.webp":{"expires":1715525935757},"_astro/side-kick-1.0b795058_VvmpS.jpg":{"expires":1715525935756},"_astro/stoneway.7e27c467_Z1herds.jpg":{"expires":1715525935757},"_astro/menu-1.2f13b7d0_Z1Htm6W.jpg":{"expires":1715525935757},"_astro/neighborhood-delivery-menu.b3b000d8_Z2lxbnd.webp":{"expires":1715525935757},"_astro/menu-hero.529ad811_2uv9Gy.webp":{"expires":1715525935755},"_astro/hero.3199ec64_wOj7O.jpg":{"expires":1715525935755},"_astro/menu-2.0aa14460_Z2pmDlp.jpg":{"expires":1715525935757},"_astro/side-kick-1.0b795058_ZJ8DUS.jpg":{"expires":1715525935756},"_astro/menu-3.e602c7de_DikqW.webp":{"expires":1715525935757},"_astro/menu-1.2f13b7d0_Z1wJ0dm.jpg":{"expires":1715525935757},"_astro/stoneway.7e27c467_27iFeH.jpg":{"expires":1715525935757},"_astro/menu-hero.529ad811_Z1kCWfb.webp":{"expires":1715525935755},"_astro/hero.3199ec64_CUHhp.jpg":{"expires":1715525935755},"_astro/menu-2.0aa14460_25EWw5.jpg":{"expires":1715525935757},"_astro/side-kick-1.0b795058_1GxPW2.jpg":{"expires":1715525935756},"_astro/menu-3.e602c7de_Z10sdVP.jpg":{"expires":1715525935757},"_astro/menu-1.2f13b7d0_Z8TIqt.jpg":{"expires":1715525935757},"_astro/stoneway.7e27c467_Z1b8uou.jpg":{"expires":1715525935757},"_astro/rainbow-spread.35f6e4c7_Z2uN5Vi.avif":{"expires":1715525936577},"_astro/hero.3199ec64_1hBjMK.jpg":{"expires":1715525935755},"_astro/menu-2.0aa14460_unVDG.jpg":{"expires":1715525935757},"_astro/side-kick-1.0b795058_Z1sohht.jpg":{"expires":1715525935756},"_astro/menu-3.e602c7de_ZWqlx.jpg":{"expires":1715525935757},"_astro/menu-1.2f13b7d0_ZKEhLb.jpg":{"expires":1715525935757},"_astro/menu-hero.529ad811_1XRDaU.webp":{"expires":1715525935755},"_astro/neighborhood-delivery-menu.b3b000d8_Z1bT3Ck.webp":{"expires":1715525935757},"_astro/stoneway.7e27c467_LEsv5.jpg":{"expires":1715525935757},"_astro/rainbow-spread.35f6e4c7_1cCDEV.webp":{"expires":1715525936577},"_astro/menu-hero.529ad811_2trcrA.jpg":{"expires":1715525935755},"_astro/menu-2.0aa14460_Z7lBG1.jpg":{"expires":1715525935757},"_astro/menu-3.e602c7de_1esG2w.jpg":{"expires":1715525935757},"_astro/neighborhood-delivery-menu.b3b000d8_Z8piqQ.jpg":{"expires":1715525935757},"_astro/menu-hero.529ad811_Z6cptU.jpg":{"expires":1715525935755},"_astro/neighborhood-delivery-menu.b3b000d8_1vwyih.jpg":{"expires":1715525935757},"_astro/menu-3.e602c7de_BI7GO.jpg":{"expires":1715525935757},"_astro/menu-hero.529ad811_Z1iI2XF.jpg":{"expires":1715525935755},"_astro/neighborhood-delivery-menu.b3b000d8_Z26gUTp.jpg":{"expires":1715525935757},"_astro/rainbow-spread.35f6e4c7_1AMo7P.webp":{"expires":1715525936577},"_astro/neighborhood-delivery-menu.b3b000d8_2maDyO.jpg":{"expires":1715525935757},"_astro/rainbow-spread.35f6e4c7_ZtI44s.webp":{"expires":1715525936577},"_astro/bagel-paper.e6d51f9b_feHi6.avif":{"expires":1715525935755},"_astro/bagel-paper.e6d51f9b_Voi00.webp":{"expires":1715525935755},"_astro/bagel-paper.e6d51f9b_12l3jQ.webp":{"expires":1715525935755},"_astro/bagel-paper.e6d51f9b_Z10KaWL.jpg":{"expires":1715525935755},"_astro/bagel-paper.e6d51f9b_ZPy5fc.jpg":{"expires":1715525935755},"_astro/rainbow-spread.35f6e4c7_Z1HGJTx.webp":{"expires":1715525936577},"_astro/rainbow-spread.35f6e4c7_ZpORbb.png":{"expires":1715525936577},"_astro/bagel-paper.e6d51f9b_ZFlaO9.avif":{"expires":1715525935755},"_astro/rainbow-spread.35f6e4c7_140bPr.png":{"expires":1715525936577},"_astro/rainbow-spread.35f6e4c7_Z1iccIj.png":{"expires":1715525936577},"_astro/rainbow-spread.35f6e4c7_1BuiAa.png":{"expires":1715525936577},"_astro/bagel-paper.e6d51f9b_4R7LB.avif":{"expires":1715525935755},"_astro/rainbow-spread.35f6e4c7_Z1OU0zQ.avif":{"expires":1715525936577},"_astro/rainbow-spread.35f6e4c7_Z1qKg7W.avif":{"expires":1715525936577},"_astro/rainbow-spread.35f6e4c7_Z12NEy6.webp":{"expires":1715525936577},"_astro/rainbow-spread.35f6e4c7_ZDDU6c.webp":{"expires":1715525936577},"_astro/rainbow-spread.35f6e4c7_tL11X.png":{"expires":1715525936577},"_astro/rainbow-spread.35f6e4c7_1XB53A.png":{"expires":1715525936577},"_astro/bagel-paper.e6d51f9b_Z1zYtv9.avif":{"expires":1715525935755},"_astro/bagel-paper.e6d51f9b_6KacB.webp":{"expires":1715525935755},"_astro/bagel-paper.e6d51f9b_QXsNm.webp":{"expires":1715525935755},"_astro/bagel-paper.e6d51f9b_ZMS8to.webp":{"expires":1715525935755},"_astro/bagel-paper.e6d51f9b_1fGDYB.jpg":{"expires":1715525935755},"_astro/bagel-paper.e6d51f9b_Z2tWoXR.jpg":{"expires":1715525935755},"_astro/bagel-paper.e6d51f9b_SSn4R.jpg":{"expires":1715525935755}}